glfw/GLFW.py
glfw/__init__.py
glfw/library.py
glfw/wayland/libglfw.so
glfw/x11/libglfw.so
glfw-2.10.0.dist-info/LICENSE.txt
glfw-2.10.0.dist-info/METADATA
glfw-2.10.0.dist-info/WHEEL
glfw-2.10.0.dist-info/top_level.txt
glfw-2.10.0.dist-info/RECORD
