Metadata-Version: 2.1
Name: glfw
Version: 2.10.0
Summary: A ctypes-based wrapper for GLFW3.
Home-page: https://github.com/FlorianRhiem/pyGLFW
Author: Florian Rhiem
Author-email: florian.rhiem@gmail.com
License: MIT
Classifier: Development Status :: 5 - Production/Stable
Classifier: Environment :: MacOS X
Classifier: Environment :: X11 Applications
Classifier: Intended Audience :: Developers
Classifier: License :: OSI Approved :: MIT License
Classifier: Programming Language :: Python :: 2
Classifier: Programming Language :: Python :: 3
Classifier: Topic :: Multimedia :: Graphics
Classifier: Topic :: Scientific/Engineering :: Visualization
Provides-Extra: preview
License-File: LICENSE.txt
